{
    "AX": {
        "error": 0.05253727882451081, 
        "fit": "average_SEM", 
        "value": -0.025743932454376287
    }, 
    "CDD": {
        "error": 0.00017511118942372834, 
        "fit": "average_SEM", 
        "value": 0.00023011364343498522
    }, 
    "H1": {
        "error": 0.13633721144939523, 
        "fit": "average_SEM", 
        "value": 0.16733986841281875
    }, 
    "H2": {
        "error": 0.11359088386885012, 
        "fit": "average_SEM", 
        "value": -0.06909642422009105
    }, 
    "L1": {
        "error": 0.25019586316543174, 
        "fit": "average_SEM", 
        "value": 0.18033941719525803
    }, 
    "L2": {
        "error": 0.11860724940866649, 
        "fit": "average_SEM", 
        "value": 0.2186891477574439
    }
}