{
    "Ar36": {
        "error": 0.00086056513599256951, 
        "fit": "parabolic", 
        "value": 0.0007933243802963493
    }, 
    "Ar37": {
        "error": 0.1318167227896479, 
        "fit": "linear", 
        "value": 0.18946140625484964
    }, 
    "Ar38": {
        "error": 0.19527828918697931, 
        "fit": "linear", 
        "value": 0.14606452524270486
    }, 
    "Ar39": {
        "error": 0.059145077173673566, 
        "fit": "parabolic", 
        "value": 0.017019191169262024
    }, 
    "Ar40": {
        "error": 0.13567834987612923, 
        "fit": "parabolic", 
        "value": 0.35518981829685348
    }, 
    "Ar41": {
        "error": 0.1293346952771616, 
        "fit": "average_SEM", 
        "value": 0.11119322114274838
    }
}