{
    "Ar36": {
        "error": 0.00076177250545510428, 
        "fit": "parabolic", 
        "value": 0.00055165486407974943
    }, 
    "Ar37": {
        "error": 0.14053081201454765, 
        "fit": "linear", 
        "value": 0.058285516219467447
    }, 
    "Ar38": {
        "error": 0.12988100642036965, 
        "fit": "linear", 
        "value": 0.054375222048359387
    }, 
    "Ar39": {
        "error": 0.055602311226789415, 
        "fit": "parabolic", 
        "value": 0.0033502962310245207
    }, 
    "Ar40": {
        "error": 0.13238412355939902, 
        "fit": "parabolic", 
        "value": 0.24945826612864869
    }, 
    "Ar41": {
        "error": 0.13282336203690417, 
        "fit": "average_SEM", 
        "value": -0.16462690164073138
    }
}