{
    "Ar36": {
        "error": 0.0017856221623750942, 
        "fit": "parabolic", 
        "value": 0.012313074099124213
    }, 
    "Ar37": {
        "error": 0.12950140858108863, 
        "fit": "linear", 
        "value": 0.6173266620459984
    }, 
    "Ar38": {
        "error": 0.21216364590568942, 
        "fit": "linear", 
        "value": 2.2614245137019027
    }, 
    "Ar39": {
        "error": 0.12100545931814997, 
        "fit": "parabolic", 
        "value": 166.18925372588211
    }, 
    "Ar40": {
        "error": 0.45555350622629082, 
        "fit": "parabolic", 
        "value": 1330.4478693937108
    }, 
    "Ar41": {
        "error": 0.12907709291487104, 
        "fit": "average_SEM", 
        "value": -0.038840550292734408
    }
}