{
    "Ar36": {
        "error": 0.001291490975692366, 
        "fit": "linear", 
        "value": 0.0064328079098399027
    }, 
    "Ar37": {
        "error": 0.1289211020361421, 
        "fit": "linear", 
        "value": 0.78837723203009946
    }, 
    "Ar38": {
        "error": 0.31068606733910487, 
        "fit": "linear", 
        "value": 2.8451294462185381
    }, 
    "Ar39": {
        "error": 0.16197073276601973, 
        "fit": "linear", 
        "value": 229.80061397183164
    }, 
    "Ar40": {
        "error": 0.53710530052936034, 
        "fit": "linear", 
        "value": 1832.0212986962902
    }, 
    "Ar41": {
        "error": 0.12669658739173031, 
        "fit": "average_SEM", 
        "value": -0.22495537680884203
    }
}