{
    "AX": {
        "error": 0.05933521717415221, 
        "fit": "average_SEM", 
        "value": -0.014600705725994582
    }, 
    "CDD": {
        "error": 0.0001345390951938621, 
        "fit": "average_SEM", 
        "value": 0.00011700693721650168
    }, 
    "H1": {
        "error": 0.12999234404796428, 
        "fit": "average_SEM", 
        "value": 0.11185989970884597
    }, 
    "H2": {
        "error": 0.11465891604481039, 
        "fit": "average_SEM", 
        "value": 0.08799225668274933
    }, 
    "L1": {
        "error": 0.1984859276648835, 
        "fit": "average_SEM", 
        "value": 0.09592926611658185
    }, 
    "L2": {
        "error": 0.13625861457736932, 
        "fit": "average_SEM", 
        "value": 0.1268242675345391
    }
}