{
    "AX": {
        "error": 0.06523914764214547, 
        "fit": "average_SEM", 
        "value": -0.01926848661484352
    }, 
    "CDD": {
        "error": 0.00028597922750910304, 
        "fit": "average_SEM", 
        "value": 0.0004108243638863011
    }, 
    "H1": {
        "error": 0.13013817543457618, 
        "fit": "average_SEM", 
        "value": 0.1501526464902175
    }, 
    "H2": {
        "error": 0.12849615086311242, 
        "fit": "average_SEM", 
        "value": -0.1080881400082338
    }, 
    "L1": {
        "error": 0.13542717023953424, 
        "fit": "average_SEM", 
        "value": 0.10452362611734618
    }, 
    "L2": {
        "error": 0.12087033643010912, 
        "fit": "average_SEM", 
        "value": 0.1291670714543822
    }
}